{
    "type": "gpu",
    "title": "MSI GeForce RTX 4060 Ti Ventus 3X E 8G OC",
    "price": 1764.6,
    "image_urls": [
        "https://static.1k.by/images/products/ip/125/pp6/d/4856589/i001c77ad6.png",
        "https://static.1k.by/images/productsimages/ip/125/pp6/d/4856589/i5c147dd9d.png",
        "https://static.1k.by/images/productsimages/ip/125/pp6/d/4856589/id98a582ff.png",
        "https://static.1k.by/images/productsimages/ip/125/pp6/d/4856589/i42f6b154f.png",
        "https://static.1k.by/images/productsimages/ip/125/pp6/d/4856589/i4c745f6f5.png"
    ],
    "data": {
        "connection_type": "PCI-E 16x",
        "manufacturer": "NVIDIA",
        "video_processor": "AD102",
        "memory_type": "GDDR6",
        "memory_size": 8192,
        "memory_frequency": 18000,
        "ray_tracing": true,
        "directx_version": "12 Ultimate",
        "opengl_version": 4.6,
        "additional_power_required": true,
        "additional_power_connector": "8 pin",
        "recommended_psu": 550
    }
}