{
    "type": "cpu",
    "title": "Intel Xeon E5-2609V4 Broadwell-EP (1700MHz, LGA2011-3, L3 20480Kb)",
    "price": 940.29,
    "image_urls": [
        "https://static.1k.by/images/products/ip/125/pp6/b/2548183/i346b67dbf.jpg"
    ],
    "data": {
        "socket": "LGA2011-3",
        "release_year": 2016,
        "core_count": 8,
        "thread_count": 8,
        "process_technology": 14,
        "integrated_graphics": false,
        "integrated_graphics_freq": 800,
        "processor_clock": 1700,
        "l2_cache_size": 2,
        "l3_cache_size": 20,
        "tdp": 85,
        "memory_type": "DDR4"
    }
}