{
    "type": "motherboard",
    "title": "ASRock B550 Phantom Gaming-ITX/ax",
    "price": 579.0,
    "image_urls": [
        "https://static.1k.by/images/products/ip/125/pp6/4/4211369/i0fc475cef.jpg",
        "https://static.1k.by/images/productsimages/ip/125/pp6/4/4211369/i06198b813.jpg",
        "https://static.1k.by/images/productsimages/ip/125/pp6/4/4211369/ie366afb01.jpg",
        "https://static.1k.by/images/productsimages/ip/125/pp6/4/4211369/i87d2ec5a5.jpg"
    ],
    "data": {
        "socket": "AM4",
        "memory_type": "DDR4 DIMM",
        "max_memory": 64,
        "memory_slots": 2,
        "max_memory_frequency": 5000,
        "dual_channel": true,
        "chipset_name": "AMD B550",
        "uefi_support": true,
        "sata_slots": 4,
        "m2_slots": 2,
        "usb_ports_total": 10,
        "main_power_connector": "24-pin",
        "cpu_power_connector": "8-pin",
        "form_factor": "mini-ITX"
    }
}