{
    "type": "motherboard",
    "title": "MSI A520M-A PRO",
    "price": 201.3,
    "image_urls": [
        "https://static.1k.by/images/products/ip/125/ppc/b/4414943/iaa999f64a.jpg",
        "https://static.1k.by/images/productsimages/ip/125/ppc/b/4414943/i64016de11.jpg",
        "https://static.1k.by/images/productsimages/ip/125/ppc/b/4414943/i4b1f48230.jpg",
        "https://static.1k.by/images/productsimages/ip/125/ppc/b/4414943/i9baa0467e.jpg",
        "https://static.1k.by/images/productsimages/ip/125/ppc/b/4414943/icdbee905e.jpg"
    ],
    "data": {
        "socket": "AM4",
        "memory_type": "DDR4 DIMM",
        "max_memory": 64,
        "memory_slots": 2,
        "max_memory_frequency": 4600,
        "dual_channel": true,
        "chipset_name": "AMD A520",
        "uefi_support": true,
        "sata_slots": 4,
        "m2_slots": 1,
        "usb_ports_total": 12,
        "main_power_connector": "24-pin",
        "cpu_power_connector": "4-pin",
        "form_factor": "mATX"
    }
}